[{"city": "Z\u00e9goua", "latitude": 10.48804, "longitude": -5.64943, "state": "Sikasso"}, {"city": "Youwarou", "latitude": 15.3684, "longitude": -4.2628, "state": "Mopti"}, {"city": "Yorosso", "latitude": 12.35811, "longitude": -4.77688, "state": "Sikasso"}, {"city": "Y\u00e9liman\u00e9", "latitude": 15.11868, "longitude": -10.57729, "state": "Kayes"}, {"city": "Yanfolila", "latitude": 11.18333, "longitude": -8.15, "state": "Sikasso"}, {"city": "Toubakoura", "latitude": 13.4637, "longitude": -7.38278, "state": "Koulikoro"}, {"city": "Tominian", "latitude": 13.28737, "longitude": -4.59317, "state": "S\u00e9gou"}, {"city": "Timbuktu", "latitude": 16.77348, "longitude": -3.00742, "state": "Tombouctou"}, {"city": "Tessalit", "latitude": 20.20126, "longitude": 1.01186, "state": "Kidal"}, {"city": "T\u00e9nenkou", "latitude": 14.45722, "longitude": -4.9169, "state": "Mopti"}, {"city": "Taoudenni", "latitude": 22.67443, "longitude": -3.97891, "state": "Taoud\u00e9nit"}, {"city": "Sokolo", "latitude": 14.7328, "longitude": -6.1219, "state": "S\u00e9gou"}, {"city": "Siribala Coro", "latitude": 14.0432, "longitude": -6.1067, "state": "S\u00e9gou"}, {"city": "Sirakoro M\u00e9gu\u00e9tana", "latitude": 12.56439, "longitude": -7.91551, "state": "Koulikoro"}, {"city": "Sikasso", "latitude": 11.31755, "longitude": -5.66654, "state": null}, {"city": "Sagala", "latitude": 14.11266, "longitude": -6.72865, "state": "S\u00e9gou"}, {"city": "S\u00e9gou", "latitude": 13.44032, "longitude": -6.25947, "state": null}, {"city": "San", "latitude": 13.30335, "longitude": -4.89562, "state": "S\u00e9gou"}, {"city": "Sagalo", "latitude": 12.2, "longitude": -10.7, "state": "Kayes"}, {"city": "Ntossoni", "latitude": 12.5304, "longitude": -5.77003, "state": "Sikasso"}, {"city": "Nioro", "latitude": 15.22932, "longitude": -9.59277, "state": "Kayes"}, {"city": "Niono", "latitude": 14.25054, "longitude": -5.98679, "state": "S\u00e9gou"}, {"city": "Niafunk\u00e9", "latitude": 15.9322, "longitude": -3.9906, "state": "Tombouctou"}, {"city": "N'D\u00e9bougou", "latitude": 14.37388, "longitude": -5.97821, "state": "S\u00e9gou"}, {"city": "Nara", "latitude": 15.16875, "longitude": -7.28466, "state": "Koulikoro"}, {"city": "Mopti", "latitude": 14.4843, "longitude": -4.18296, "state": null}, {"city": "Molodo", "latitude": 14.23719, "longitude": -6.02269, "state": "S\u00e9gou"}, {"city": "M\u00e9naka", "latitude": 15.9182, "longitude": 2.4022, "state": null}, {"city": "Markala", "latitude": 13.68427, "longitude": -6.07352, "state": "S\u00e9gou"}, {"city": "Moribabougou", "latitude": 12.68672, "longitude": -7.86378, "state": "Koulikoro"}, {"city": "Koutiala", "latitude": 12.39173, "longitude": -5.46421, "state": "Sikasso"}, {"city": "Kouri", "latitude": 12.18396, "longitude": -4.80284, "state": "Sikasso"}, {"city": "Koulikoro", "latitude": 12.86273, "longitude": -7.55985, "state": null}, {"city": "Koula", "latitude": 13.11382, "longitude": -7.65231, "state": "Koulikoro"}, {"city": "Koro", "latitude": 14.064, "longitude": -3.07539, "state": "Mopti"}, {"city": "Kolondi\u00e9ba", "latitude": 11.08943, "longitude": -6.8929, "state": "Sikasso"}, {"city": "Kolokani", "latitude": 13.5728, "longitude": -8.0339, "state": "Koulikoro"}, {"city": "Kokofata", "latitude": 12.88333, "longitude": -9.95, "state": "Kayes"}, {"city": "Kita", "latitude": 13.0349, "longitude": -9.4895, "state": "Kayes"}, {"city": "Kidal", "latitude": 18.44111, "longitude": 1.40778, "state": null}, {"city": "K\u00e8n\u00e8nkoun", "latitude": 13.10624, "longitude": -7.24337, "state": "Koulikoro"}, {"city": "Kinmparana", "latitude": 12.84217, "longitude": -4.9245, "state": "S\u00e9gou"}, {"city": "K\u00e9-Macina", "latitude": 13.9641, "longitude": -5.35791, "state": "S\u00e9gou"}, {"city": "Kayes", "latitude": 14.44693, "longitude": -11.44448, "state": null}, {"city": "Kati", "latitude": 12.74409, "longitude": -8.07257, "state": "Koulikoro"}, {"city": "Kangaba", "latitude": 11.93333, "longitude": -8.41667, "state": "Koulikoro"}, {"city": "Kalaban Koro", "latitude": 12.57329, "longitude": -8.02907, "state": "Koulikoro"}, {"city": "Kadiolo", "latitude": 10.55, "longitude": -5.76667, "state": "Sikasso"}, {"city": "Kabala", "latitude": 12.52549, "longitude": -8.03927, "state": "Koulikoro"}, {"city": "Gourma Rharous", "latitude": 16.87778, "longitude": -1.92306, "state": "Tombouctou"}, {"city": "Goundam", "latitude": 16.41453, "longitude": -3.67075, "state": "Tombouctou"}, {"city": "Gao", "latitude": 16.27167, "longitude": -0.04472, "state": null}, {"city": "P\u00e8l\u00e8ngana", "latitude": 13.4274, "longitude": -6.222, "state": "S\u00e9gou"}, {"city": "Fana", "latitude": 12.7787, "longitude": -6.9564, "state": "Koulikoro"}, {"city": "Doumba", "latitude": 13.1042, "longitude": -7.61121, "state": "Koulikoro"}, {"city": "Douentza", "latitude": 15.00155, "longitude": -2.94978, "state": "Mopti"}, {"city": "Dougabougou", "latitude": 13.82049, "longitude": -6.12057, "state": "S\u00e9gou"}, {"city": "Djenn\u00e9", "latitude": 13.90608, "longitude": -4.55332, "state": "Mopti"}, {"city": "Dir\u00e9", "latitude": 16.25705, "longitude": -3.40126, "state": "Tombouctou"}, {"city": "Diourou", "latitude": 13.68719, "longitude": -5.83203, "state": "S\u00e9gou"}, {"city": "Dioila", "latitude": 12.4822, "longitude": -6.7911, "state": "Koulikoro"}, {"city": "Di\u00e9ma", "latitude": 14.54, "longitude": -9.1921, "state": "Kayes"}, {"city": "Bourem", "latitude": 16.955, "longitude": -0.34861, "state": "Gao"}, {"city": "Bougouni", "latitude": 11.41769, "longitude": -7.48323, "state": "Sikasso"}, {"city": "Bla", "latitude": 12.95007, "longitude": -5.76024, "state": "S\u00e9gou"}, {"city": "Barou\u00e9li", "latitude": 13.077, "longitude": -6.8312, "state": "S\u00e9gou"}, {"city": "Bankass", "latitude": 14.0775, "longitude": -3.51594, "state": "Mopti"}, {"city": "Bandiagara", "latitude": 14.35005, "longitude": -3.61038, "state": "Mopti"}, {"city": "Banamba", "latitude": 13.54773, "longitude": -7.44808, "state": "Koulikoro"}, {"city": "Bamako", "latitude": 12.65, "longitude": -8.0, "state": null}, {"city": "Bafoulab\u00e9", "latitude": 13.8065, "longitude": -10.8321, "state": "Kayes"}, {"city": "Araouane", "latitude": 18.90476, "longitude": -3.52649, "state": "Tombouctou"}, {"city": "Ansongo", "latitude": 15.6597, "longitude": 0.5022, "state": "Gao"}, {"city": "Dialakorodji", "latitude": 12.70354, "longitude": -7.96463, "state": "Koulikoro"}, {"city": "Abe\u00efbara", "latitude": 19.11667, "longitude": 1.75, "state": "Kidal"}, {"city": "In\u00e9kar", "latitude": 15.95944, "longitude": 3.14111, "state": "Gao"}, {"city": "Ti-n-Essako", "latitude": 18.45059, "longitude": 2.48795, "state": "Kidal"}, {"city": "Leleni", "latitude": 12.38944, "longitude": -5.24528, "state": "Sikasso"}, {"city": "Figuira-Toma", "latitude": 11.91667, "longitude": -8.36667, "state": "Bamako"}, {"city": "Werekela", "latitude": 14.33263, "longitude": -5.94515, "state": "S\u00e9gou"}, {"city": "Zambla", "latitude": 10.24245, "longitude": -6.98682, "state": "Sikasso"}, {"city": "Massiogo", "latitude": 10.30635, "longitude": -6.10972, "state": "Sikasso"}, {"city": "Sangar\u00e9bougou", "latitude": 12.70581, "longitude": -7.90268, "state": "Koulikoro"}]