[{"city": "Yio Chu Kang", "latitude": 1.39111, "longitude": 103.85139, "state": null}, {"city": "Yew Tee", "latitude": 1.39444, "longitude": 103.75389, "state": null}, {"city": "West Coast Village", "latitude": 1.31667, "longitude": 103.75, "state": null}, {"city": "Mount Vernon", "latitude": 1.33583, "longitude": 103.8975, "state": null}, {"city": "Ulu Bedok", "latitude": 1.33333, "longitude": 103.93333, "state": null}, {"city": "Toa Payoh New Town", "latitude": 1.33611, "longitude": 103.85, "state": null}, {"city": "Tiong Bahru Estate", "latitude": 1.28333, "longitude": 103.83278, "state": null}, {"city": "Thomson", "latitude": 1.34917, "longitude": 103.84361, "state": null}, {"city": "Tanglin", "latitude": 1.31667, "longitude": 103.81667, "state": null}, {"city": "Tampines Estate", "latitude": 1.35806, "longitude": 103.94028, "state": null}, {"city": "Tai Seng", "latitude": 1.33611, "longitude": 103.90361, "state": null}, {"city": "Sungai Simpang", "latitude": 1.43806, "longitude": 103.82667, "state": null}, {"city": "Somapah Changi", "latitude": 1.34167, "longitude": 103.96361, "state": null}, {"city": "Singapore", "latitude": 1.28967, "longitude": 103.85007, "state": null}, {"city": "Serangoon Garden Estate", "latitude": 1.36389, "longitude": 103.8575, "state": null}, {"city": "Serangoon", "latitude": 1.36278, "longitude": 103.8975, "state": null}, {"city": "Sennett Estate", "latitude": 1.33194, "longitude": 103.87167, "state": null}, {"city": "Sembawang Hills Estate", "latitude": 1.37278, "longitude": 103.83028, "state": null}, {"city": "Sembawang Estate", "latitude": 1.45083, "longitude": 103.82861, "state": null}, {"city": "Punggol", "latitude": 1.41444, "longitude": 103.90694, "state": null}, {"city": "Paya Lebar", "latitude": 1.35389, "longitude": 103.89056, "state": null}, {"city": "Pasir Panjang", "latitude": 1.29278, "longitude": 103.77083, "state": null}, {"city": "Matilda Estate", "latitude": 1.39944, "longitude": 103.90278, "state": null}, {"city": "Marsiling", "latitude": 1.44111, "longitude": 103.77083, "state": null}, {"city": "Loyang", "latitude": 1.37861, "longitude": 103.97167, "state": null}, {"city": "Leedon Park", "latitude": 1.31694, "longitude": 103.79417, "state": null}, {"city": "Lam San Village", "latitude": 1.37694, "longitude": 103.73139, "state": null}, {"city": "Keat Hong Village", "latitude": 1.37778, "longitude": 103.74417, "state": null}, {"city": "Kampong Ulu Pandan", "latitude": 1.34611, "longitude": 103.745, "state": null}, {"city": "Kampong Ubi", "latitude": 1.31667, "longitude": 103.9, "state": null}, {"city": "Kampong Potong Pasir", "latitude": 1.33333, "longitude": 103.86667, "state": null}, {"city": "Kampong Pasir Ris", "latitude": 1.37833, "longitude": 103.93194, "state": null}, {"city": "Kampong Loyang", "latitude": 1.37778, "longitude": 103.95944, "state": null}, {"city": "Kembangan", "latitude": 1.32228, "longitude": 103.91135, "state": null}, {"city": "Kampong Java Teban", "latitude": 1.33333, "longitude": 103.73333, "state": null}, {"city": "Kalang", "latitude": 1.33333, "longitude": 103.86667, "state": null}, {"city": "Hong Kah", "latitude": 1.35944, "longitude": 103.72278, "state": null}, {"city": "Holland Village", "latitude": 1.31194, "longitude": 103.79333, "state": null}, {"city": "Geylang", "latitude": 1.31953, "longitude": 103.88689, "state": null}, {"city": "Changi Village", "latitude": 1.39037, "longitude": 103.98674, "state": null}, {"city": "Bulim", "latitude": 1.37444, "longitude": 103.71778, "state": null}, {"city": "Bukit Timah Estate", "latitude": 1.34028, "longitude": 103.77583, "state": null}, {"city": "Bukit Merah Estate", "latitude": 1.28417, "longitude": 103.82306, "state": null}, {"city": "Bukit Mandai Village", "latitude": 1.41222, "longitude": 103.75667, "state": null}, {"city": "Brickworks Estate", "latitude": 1.28722, "longitude": 103.80833, "state": null}, {"city": "Braddell Heights Estate", "latitude": 1.34528, "longitude": 103.86528, "state": null}, {"city": "Boon Lay", "latitude": 1.311, "longitude": 103.694, "state": null}, {"city": "Alexandra Estate", "latitude": 1.29389, "longitude": 103.81972, "state": null}, {"city": "Bishan New Town", "latitude": 1.3504, "longitude": 103.84875, "state": null}, {"city": "Bukit Batok New Town", "latitude": 1.35903, "longitude": 103.76368, "state": null}, {"city": "Bukit Ho Swee Estate", "latitude": 1.28778, "longitude": 103.83, "state": null}, {"city": "Henderson Estate", "latitude": 1.28917, "longitude": 103.82333, "state": null}, {"city": "Hougang New Town", "latitude": 1.35667, "longitude": 103.89083, "state": null}, {"city": "Jurong East", "latitude": 1.32888, "longitude": 103.73995, "state": null}, {"city": "Jurong Town", "latitude": 1.33417, "longitude": 103.72278, "state": null}, {"city": "Jurong West", "latitude": 1.35028, "longitude": 103.72278, "state": null}, {"city": "Kaki Bukit Estate", "latitude": 1.3375, "longitude": 103.90917, "state": null}, {"city": "MacPherson", "latitude": 1.32713, "longitude": 103.88413, "state": null}, {"city": "Outram Park", "latitude": 1.2825, "longitude": 103.83806, "state": null}, {"city": "Serangoon New Town", "latitude": 1.35083, "longitude": 103.87083, "state": null}, {"city": "Simei New Town", "latitude": 1.34111, "longitude": 103.95611, "state": null}, {"city": "Tampines New Town", "latitude": 1.34917, "longitude": 103.94972, "state": null}, {"city": "Tanglin Halt", "latitude": 1.30139, "longitude": 103.7975, "state": null}, {"city": "Yishun New Town", "latitude": 1.43333, "longitude": 103.83111, "state": null}, {"city": "Woodlands", "latitude": 1.43801, "longitude": 103.78877, "state": null}, {"city": "Kangkar", "latitude": 1.37611, "longitude": 103.90167, "state": null}, {"city": "Hillcrest Park", "latitude": 1.33472, "longitude": 103.80917, "state": null}, {"city": "Pandan Valley", "latitude": 1.31833, "longitude": 103.77583, "state": null}, {"city": "Faber Hills", "latitude": 1.32083, "longitude": 103.75972, "state": null}, {"city": "Ghim Moh", "latitude": 1.31111, "longitude": 103.78778, "state": null}, {"city": "Mount Emily Park", "latitude": 1.30472, "longitude": 103.84722, "state": null}, {"city": "Lucky Hills", "latitude": 1.32556, "longitude": 103.95278, "state": null}, {"city": "Marine Parade", "latitude": 1.30306, "longitude": 103.90778, "state": null}, {"city": "Ang Mo Kio New Town", "latitude": 1.38028, "longitude": 103.83972, "state": null}, {"city": "Bukit Panjang New Town", "latitude": 1.37972, "longitude": 103.76472, "state": null}, {"city": "Bedok New Town", "latitude": 1.32639, "longitude": 103.94167, "state": null}, {"city": "Clementi Housing Estate", "latitude": 1.31583, "longitude": 103.76472, "state": null}, {"city": "Pasir Ris New Town", "latitude": 1.37222, "longitude": 103.94778, "state": null}, {"city": "Queenstown Estate", "latitude": 1.29417, "longitude": 103.8025, "state": null}, {"city": "Telok Blangah New Town", "latitude": 1.27472, "longitude": 103.81167, "state": null}, {"city": "Choa Chu Kang New Town", "latitude": 1.3825, "longitude": 103.74972, "state": null}, {"city": "Novena", "latitude": 1.31697, "longitude": 103.8438, "state": null}, {"city": "Eunos", "latitude": 1.32252, "longitude": 103.89822, "state": null}, {"city": "Admiralty", "latitude": 1.44069, "longitude": 103.80093, "state": null}, {"city": "Lavender", "latitude": 1.30717, "longitude": 103.86301, "state": null}, {"city": "Newton", "latitude": 1.30902, "longitude": 103.83757, "state": null}, {"city": "Sengkang New Town", "latitude": 1.39167, "longitude": 103.89444, "state": null}, {"city": "HarbourFront", "latitude": 1.2652, "longitude": 103.8201, "state": null}, {"city": "Marina Bay", "latitude": 1.28105, "longitude": 103.85972, "state": null}, {"city": "Sentosa", "latitude": 1.24969, "longitude": 103.83119, "state": null}, {"city": "River Valley", "latitude": 1.29606, "longitude": 103.83608, "state": null}]