[{"city": "Trindade", "latitude": 0.29667, "longitude": 6.68139, "state": "S\u00e3o Tom\u00e9 Island"}, {"city": "S\u00e3o Tom\u00e9", "latitude": 0.33654, "longitude": 6.72732, "state": "S\u00e3o Tom\u00e9 Island"}, {"city": "S\u00e3o Jo\u00e3o dos Angolares", "latitude": 0.13417, "longitude": 6.64944, "state": "S\u00e3o Tom\u00e9 Island"}, {"city": "Santo Ant\u00f3nio", "latitude": 1.63943, "longitude": 7.41951, "state": "Pr\u00edncipe"}, {"city": "Neves", "latitude": 0.35671, "longitude": 6.54897, "state": "S\u00e3o Tom\u00e9 Island"}, {"city": "Guadalupe", "latitude": 0.37917, "longitude": 6.6375, "state": "S\u00e3o Tom\u00e9 Island"}, {"city": "\u00c1gua Iz\u00e9", "latitude": 0.21667, "longitude": 6.73333, "state": "S\u00e3o Tom\u00e9 Island"}, {"city": "Folha Fede", "latitude": 0.284, "longitude": 6.684, "state": "S\u00e3o Tom\u00e9 Island"}, {"city": "Almas", "latitude": 0.29907, "longitude": 6.74467, "state": "S\u00e3o Tom\u00e9 Island"}, {"city": "Changra", "latitude": 0.34985, "longitude": 6.68657, "state": "S\u00e3o Tom\u00e9 Island"}, {"city": "Cova Barro", "latitude": 0.31499, "longitude": 6.7383, "state": "S\u00e3o Tom\u00e9 Island"}, {"city": "Micondo", "latitude": 0.17121, "longitude": 6.67729, "state": "S\u00e3o Tom\u00e9 Island"}, {"city": "Pantufo", "latitude": 0.31503, "longitude": 6.74348, "state": "S\u00e3o Tom\u00e9 Island"}]